Metadata-Version: 2.1
Name: Mensajes-yeru
Version: 5.0
Summary: Un paquete para saludar y despedir
Home-page: https://www.hector.dev
Author: Hector costa guzman
Author-email: Hola@hector.dev
Classifier: Environment :: Console
Classifier: Intended Audience :: Developers
Classifier: License :: OSI Approved :: MIT License
Classifier: Operating System :: OS Independent
Classifier: Programming Language :: Python
Classifier: Programming Language :: Python :: 3.9
Classifier: Topic :: Utilities
License-File: LICENSE
Requires-Dist: numpy >=1.24.3
